[
    {
        "inputs": [
            {
                "internalType": "address",
                "name": "tokenAddress",
                "type": "address"
            }
        ],
        "stateMutability": "nonpayable",
        "type": "constructor"
    },
    {
        "inputs": [],
        "name": "ControllerNotFound",
        "type": "error"
    },
    {
        "inputs": [],
        "name": "InsufficientTokens",
        "type": "error"
    },
    {
        "inputs": [],
        "name": "InvalidAddress",
        "type": "error"
    },
    {
        "inputs": [],
        "name": "InvalidAmount",
        "type": "error"
    },
    {
        "inputs": [],
        "name": "InvalidCliff",
        "type": "error"
    },
    {
        "inputs": [],
        "name": "NoTokensToRelease",
        "type": "error"
    },
    {
        "inputs": [],
        "name": "NoVestedTokens",
        "type": "error"
    },
    {
        "inputs": [],
        "name": "ReentrancyGuardReentrantCall",
        "type": "error"
    },
    {
        "inputs": [],
        "name": "TokenAlreadySet",
        "type": "error"
    },
    {
        "inputs": [],
        "name": "UnauthorizedAccess",
        "type": "error"
    },
    {
        "anonymous": false,
        "inputs": [
            {
                "indexed": false,
                "internalType": "address",
                "name": "controller",
                "type": "address"
            }
        ],
        "name": "ControllerAdded",
        "type": "event"
    },
    {
        "anonymous": false,
        "inputs": [
            {
                "indexed": false,
                "internalType": "address",
                "name": "controller",
                "type": "address"
            }
        ],
        "name": "ControllerRemoved",
        "type": "event"
    },
    {
        "anonymous": false,
        "inputs": [
            {
                "indexed": true,
                "internalType": "address",
                "name": "beneficiary",
                "type": "address"
            },
            {
                "indexed": false,
                "internalType": "uint256",
                "name": "amount",
                "type": "uint256"
            }
        ],
        "name": "TokensReleased",
        "type": "event"
    },
    {
        "anonymous": false,
        "inputs": [
            {
                "indexed": true,
                "internalType": "address",
                "name": "beneficiary",
                "type": "address"
            },
            {
                "indexed": false,
                "internalType": "uint256",
                "name": "totalAmount",
                "type": "uint256"
            },
            {
                "indexed": false,
                "internalType": "uint256",
                "name": "start",
                "type": "uint256"
            },
            {
                "indexed": false,
                "internalType": "uint256",
                "name": "cliff",
                "type": "uint256"
            },
            {
                "indexed": false,
                "internalType": "uint256",
                "name": "duration",
                "type": "uint256"
            }
        ],
        "name": "VestingAdded",
        "type": "event"
    },
    {
        "inputs": [
            {
                "internalType": "address[]",
                "name": "newControllers",
                "type": "address[]"
            }
        ],
        "name": "addControllers",
        "outputs": [],
        "stateMutability": "nonpayable",
        "type": "function"
    },
    {
        "inputs": [
            {
                "internalType": "address",
                "name": "beneficiary",
                "type": "address"
            },
            {
                "internalType": "uint256",
                "name": "totalAmount",
                "type": "uint256"
            },
            {
                "internalType": "uint256",
                "name": "start",
                "type": "uint256"
            },
            {
                "internalType": "uint256",
                "name": "cliff",
                "type": "uint256"
            },
            {
                "internalType": "uint256",
                "name": "duration",
                "type": "uint256"
            }
        ],
        "name": "addVesting",
        "outputs": [],
        "stateMutability": "nonpayable",
        "type": "function"
    },
    {
        "inputs": [
            {
                "internalType": "address[]",
                "name": "beneficiaries",
                "type": "address[]"
            },
            {
                "internalType": "uint256[]",
                "name": "totalAmounts",
                "type": "uint256[]"
            },
            {
                "internalType": "uint256[]",
                "name": "starts",
                "type": "uint256[]"
            },
            {
                "internalType": "uint256[]",
                "name": "cliffs",
                "type": "uint256[]"
            },
            {
                "internalType": "uint256[]",
                "name": "durations",
                "type": "uint256[]"
            }
        ],
        "name": "batchAddVesting",
        "outputs": [],
        "stateMutability": "nonpayable",
        "type": "function"
    },
    {
        "inputs": [
            {
                "internalType": "address",
                "name": "",
                "type": "address"
            }
        ],
        "name": "controllers",
        "outputs": [
            {
                "internalType": "bool",
                "name": "",
                "type": "bool"
            }
        ],
        "stateMutability": "view",
        "type": "function"
    },
    {
        "inputs": [
            {
                "internalType": "address",
                "name": "beneficiary",
                "type": "address"
            }
        ],
        "name": "getVestingDetails",
        "outputs": [
            {
                "components": [
                    {
                        "internalType": "uint256",
                        "name": "totalAmount",
                        "type": "uint256"
                    },
                    {
                        "internalType": "uint256",
                        "name": "releasedAmount",
                        "type": "uint256"
                    },
                    {
                        "internalType": "uint256",
                        "name": "start",
                        "type": "uint256"
                    },
                    {
                        "internalType": "uint256",
                        "name": "cliff",
                        "type": "uint256"
                    },
                    {
                        "internalType": "uint256",
                        "name": "duration",
                        "type": "uint256"
                    }
                ],
                "internalType": "struct VestingContract.VestingSchedule[]",
                "name": "",
                "type": "tuple[]"
            }
        ],
        "stateMutability": "view",
        "type": "function"
    },
    {
        "inputs": [],
        "name": "owner",
        "outputs": [
            {
                "internalType": "address",
                "name": "",
                "type": "address"
            }
        ],
        "stateMutability": "view",
        "type": "function"
    },
    {
        "inputs": [
            {
                "internalType": "address",
                "name": "beneficiary",
                "type": "address"
            }
        ],
        "name": "releaseTokens",
        "outputs": [],
        "stateMutability": "nonpayable",
        "type": "function"
    },
    {
        "inputs": [
            {
                "internalType": "address[]",
                "name": "oldControllers",
                "type": "address[]"
            }
        ],
        "name": "removeControllers",
        "outputs": [],
        "stateMutability": "nonpayable",
        "type": "function"
    },
    {
        "inputs": [],
        "name": "token",
        "outputs": [
            {
                "internalType": "contract IERC20",
                "name": "",
                "type": "address"
            }
        ],
        "stateMutability": "view",
        "type": "function"
    },
    {
        "inputs": [
            {
                "internalType": "address",
                "name": "",
                "type": "address"
            },
            {
                "internalType": "uint256",
                "name": "",
                "type": "uint256"
            }
        ],
        "name": "vestings",
        "outputs": [
            {
                "internalType": "uint256",
                "name": "totalAmount",
                "type": "uint256"
            },
            {
                "internalType": "uint256",
                "name": "releasedAmount",
                "type": "uint256"
            },
            {
                "internalType": "uint256",
                "name": "start",
                "type": "uint256"
            },
            {
                "internalType": "uint256",
                "name": "cliff",
                "type": "uint256"
            },
            {
                "internalType": "uint256",
                "name": "duration",
                "type": "uint256"
            }
        ],
        "stateMutability": "view",
        "type": "function"
    }
]